valaw/__init__.py
valaw/client.py
valaw/objects/__init__.py
valaw/objects/account.py
valaw/objects/content.py
valaw/objects/match.py
valaw/objects/ranked.py
valaw/objects/status.py
valaw-0.1.9.dist-info/licenses/LICENSE
valaw-0.1.9.dist-info/METADATA
valaw-0.1.9.dist-info/WHEEL
valaw-0.1.9.dist-info/top_level.txt
valaw-0.1.9.dist-info/RECORD
