Metadata-Version: 2.4
Name: valaw
Version: 0.1.9
Summary: An asynchronous API wrapper for VALORANT's API
Home-page: https://github.com/Jet612/valaw
Author: Jet612
Project-URL: Source, https://github.com/Jet612/valaw
Project-URL: Documentation, https://valaw.readthedocs.io
Project-URL: Issue Tracker, https://github.com/Jet612/valaw/issues
Project-URL: Chat/Support, https://discord.gg/mVXpvunBbF
Classifier: License :: OSI Approved :: MIT License
Classifier: Programming Language :: Python :: 3.9
Classifier: Programming Language :: Python :: 3.10
Classifier: Programming Language :: Python :: 3.11
Classifier: Programming Language :: Python :: 3.12
Classifier: Operating System :: OS Independent
Classifier: Development Status :: 4 - Beta
Classifier: Intended Audience :: Developers
Classifier: Topic :: Software Development
Requires-Python: >=3.9
License-File: LICENSE
Requires-Dist: dataclass_wizard==0.35.0
Requires-Dist: aiohttp==3.11.18
Requires-Dist: setuptools==80.0.0
Dynamic: author
Dynamic: classifier
Dynamic: description
Dynamic: description-content-type
Dynamic: home-page
Dynamic: license-file
Dynamic: project-url
Dynamic: requires-dist
Dynamic: requires-python
Dynamic: summary
